nemotron_ocr/inference/__init__.py
nemotron_ocr/inference/pipeline.py
nemotron_ocr/inference/pre_processing.py
nemotron_ocr/inference/weight_downloader.py
nemotron_ocr/inference/encoders/__init__.py
nemotron_ocr/inference/encoders/base.py
nemotron_ocr/inference/encoders/recognizer_encoder.py
nemotron_ocr/inference/encoders/relational_encoder.py
nemotron_ocr/inference/models/__init__.py
nemotron_ocr/inference/models/blocks.py
nemotron_ocr/inference/models/recognizer.py
nemotron_ocr/inference/models/relational.py
nemotron_ocr/inference/models/utils.py
nemotron_ocr/inference/models/detector/__init__.py
nemotron_ocr/inference/models/detector/aspp.py
nemotron_ocr/inference/models/detector/fots_detector.py
nemotron_ocr/inference/models/detector/regnet.py
nemotron_ocr/inference/post_processing/__init__.py
nemotron_ocr/inference/post_processing/indirect_grid_sample.py
nemotron_ocr/inference/post_processing/quad_rectify.py
nemotron_ocr/inference/post_processing/research_ops.py
nemotron_ocr/inference/post_processing/rrect_to_quads.py
nemotron_ocr/inference/post_processing/data/data_container.py
nemotron_ocr/inference/post_processing/data/quadrangle.py
nemotron_ocr/inference/post_processing/data/relation_graph.py
nemotron_ocr/inference/post_processing/data/text_region.py
nemotron_ocr/inference/post_processing/data/worker_messages.py
nemotron_ocr_cpp/__init__.py
nemotron_ocr_cpp/_nemotron_ocr_cpp.cpython-312-x86_64-linux-gnu.so
nemotron_ocr-1.0.0.dist-info/METADATA
nemotron_ocr-1.0.0.dist-info/WHEEL
nemotron_ocr-1.0.0.dist-info/RECORD
