Metadata-Version: 2.4
Name: nemotron-ocr
Version: 1.0.0
Summary: Nemoton OCR
Project-URL: Homepage, https://nvidia.com/
Author: NVIDIA Nemotron
Requires-Python: <3.13,>=3.12
Requires-Dist: huggingface-hub>=0.20.0
Requires-Dist: pandas>=2.3.3
Requires-Dist: pillow>=12.0.0
Requires-Dist: scikit-learn>=1.7.2
Requires-Dist: shapely<3,>=2.1.2
Requires-Dist: torch>=2.8.0
Requires-Dist: torchvision>=0.23.0
